infoicer/__init__.py
infoicer/infoicer.py
infoicer/util.py
infoicer-0.0.1.dist-info/LICENCE.txt
infoicer-0.0.1.dist-info/METADATA
infoicer-0.0.1.dist-info/WHEEL
infoicer-0.0.1.dist-info/top_level.txt
infoicer-0.0.1.dist-info/RECORD
