Metadata-Version: 2.1
Name: infoicer
Version: 0.0.1
Summary: Infoicer is a simple invoice items handler.
Home-page: https://github.com/edkirin/infoicer
Author: Eden Kirin
Author-email: edkirin@gmail.com
License: MIT
Keywords: invoice
Platform: UNKNOWN
Classifier: Programming Language :: Python :: 3
Classifier: Programming Language :: Python :: 3.6
Classifier: Programming Language :: Python :: 3.7
Classifier: Programming Language :: Python :: 3.8
Classifier: Programming Language :: Python :: 3.9
Classifier: License :: OSI Approved :: MIT License
Classifier: Operating System :: OS Independent
Requires-Python: >=3.6
